async_icq/__init__.py
async_icq/bot.py
async_icq/constant.py
async_icq/events.py
async_icq/helpers.py
async_icq/middleware.py
async_icq-1.4.9.dist-info/licenses/LICENSE
async_icq-1.4.9.dist-info/METADATA
async_icq-1.4.9.dist-info/WHEEL
async_icq-1.4.9.dist-info/top_level.txt
async_icq-1.4.9.dist-info/RECORD
