Metadata-Version: 2.4
Name: async_icq
Version: 1.4.9
Summary: ICQ/VK Teams Bot API interface
Home-page: https://github.com/dasshit/async-icq
Author: Valerii Korobov
Author-email: dasshit@yandex.ru
Keywords: mailru im bot api
Classifier: Intended Audience :: Developers
Classifier: Topic :: Software Development :: Libraries :: Python Modules
Classifier: Topic :: Communications :: Chat
Classifier: Topic :: Internet
Classifier: Programming Language :: Python :: 3.5
Classifier: Programming Language :: Python :: 3.6
Classifier: Programming Language :: Python :: 3.7
Classifier: Programming Language :: Python :: 3.8
Classifier: Programming Language :: Python :: 3.9
Classifier: License :: OSI Approved :: MIT License
Classifier: Operating System :: OS Independent
Requires-Python: >=3.5
License-File: LICENSE
Requires-Dist: aiohttp>=3.8.1
Requires-Dist: aiologger>=0.6.1
Requires-Dist: aiosignal>=1.2.0
Requires-Dist: async-timeout>=4.0.2
Requires-Dist: attrs>=21.4.0
Requires-Dist: charset-normalizer>=2.0.10
Requires-Dist: frozenlist>=1.2.0
Requires-Dist: idna>=3.3
Requires-Dist: multidict>=5.2.0
Requires-Dist: yarl>=1.7.2
Dynamic: author
Dynamic: author-email
Dynamic: classifier
Dynamic: description
Dynamic: description-content-type
Dynamic: home-page
Dynamic: keywords
Dynamic: license-file
Dynamic: requires-dist
Dynamic: requires-python
Dynamic: summary
